AUTHORS.rst
CHANGES.rst
LICENSE.rst
MANIFEST.in
README.rst
setup.cfg
setup.py
Create_Python_Project.egg-info/PKG-INFO
Create_Python_Project.egg-info/SOURCES.txt
Create_Python_Project.egg-info/dependency_links.txt
Create_Python_Project.egg-info/entry_points.txt
Create_Python_Project.egg-info/not-zip-safe
Create_Python_Project.egg-info/requires.txt
Create_Python_Project.egg-info/top_level.txt
create_python_project/__init__.py
create_python_project/cli.py
create_python_project/config.py
create_python_project/git.py
create_python_project/info.py
create_python_project/io.py
create_python_project/project.py
create_python_project/utils.py
create_python_project/pyutils/__init__.py
create_python_project/pyutils/pep487.py
create_python_project/scripts/__init__.py
create_python_project/scripts/base.py
create_python_project/scripts/ini.py
create_python_project/scripts/init.py
create_python_project/scripts/py.py
create_python_project/scripts/rst.py
create_python_project/scripts/setup.py
create_python_project/scripts/yml.py
docs/Makefile
docs/conf.py
docs/docs/api_reference.rst
docs/docs/changelog.rst
docs/docs/contents.rst.inc
docs/docs/contributing.rst
docs/docs/index.rst
docs/docs/license.rst
tests/__init__.py
tests/conftest.py
tests/test_cli.py
tests/test_config.py
tests/test_git.py
tests/test_import.py
tests/test_info.py
tests/test_io.py
tests/test_pep487.py
tests/test_project.py
tests/test_utils.py
tests/config/.crpyprojrc
tests/repo/.coveragerc
tests/repo/.gitignore
tests/repo/.gitlab-ci.yml
tests/repo/.travis.yml
tests/repo/AUTHORS.rst
tests/repo/CHANGES.rst
tests/repo/CONTRIBUTING.rst
tests/repo/LICENSE.rst
tests/repo/Makefile
tests/repo/README.rst
tests/repo/setup.cfg
tests/repo/setup.py
tests/repo/tox.ini
tests/repo/boilerplate_python/__init__.py
tests/repo/docs/Makefile
tests/repo/docs/conf.py
tests/repo/docs/docs/api_reference.rst
tests/repo/docs/docs/changelog.rst
tests/repo/docs/docs/contents.rst.inc
tests/repo/docs/docs/contributing.rst
tests/repo/docs/docs/index.rst
tests/repo/docs/docs/license.rst
tests/repo/tests/__init__.py
tests/repo/tests/test_import.py
tests/scripts/__init__.py
tests/scripts/test_.py
tests/scripts/test_base.py
tests/scripts/test_ini.py
tests/scripts/test_init.py
tests/scripts/test_py.py
tests/scripts/test_rst.py
tests/scripts/test_setup.py
