Metadata-Version: 1.1
Name: Create-Python-Project
Version: 0.1.0
Summary: Create-Python-Project is a CLI application to facilitate Python project management
Home-page: https://github.com/nicolas-maurice/create-python-project
Author: Nicolas Maurice
Author-email: nicolas.maurice.valera@gmail.com
License: Copyright (c) 2017 by Nicolas Maurice and contributors. See AUTHORS.rst
